jmanager/__init__.py
jmanager/cli.py
jmanager/jmanager.py
jmanager-2.0.2.dist-info/LICENSE
jmanager-2.0.2.dist-info/METADATA
jmanager-2.0.2.dist-info/WHEEL
jmanager-2.0.2.dist-info/entry_points.txt
jmanager-2.0.2.dist-info/RECORD
